PdfExTools/__init__.py
PdfExTools/page_number_extractor.py
pdfextools-0.3.0.dist-info/LICENSE
pdfextools-0.3.0.dist-info/METADATA
pdfextools-0.3.0.dist-info/WHEEL
pdfextools-0.3.0.dist-info/top_level.txt
pdfextools-0.3.0.dist-info/RECORD
