Metadata-Version: 2.1
Name: pdfextools
Version: 0.3.0
Summary: A set of extended tools to process pdf files
Home-page: https://github.com/markfront/PdfExTools
Author: Mark Front
Author-email: mark.front@gmail.com
License: UNKNOWN
Platform: UNKNOWN
Classifier: Programming Language :: Python :: 3
Classifier: License :: OSI Approved :: MIT License
Classifier: Operating System :: OS Independent
Requires-Python: >=3.6
